upload/__init__.py
upload/config.py
upload/configPattern.py
upload/portDetector.py
upload/timeChecker.py
upload/uploader.py
uploader/__init__.py
uploader/configPattern.py
uploader/portDetector.py
uploader/timeChecker.py
uploader/uploader.py
micropython_uploader-0.3.2.dist-info/LICENSE
micropython_uploader-0.3.2.dist-info/METADATA
micropython_uploader-0.3.2.dist-info/WHEEL
micropython_uploader-0.3.2.dist-info/entry_points.txt
micropython_uploader-0.3.2.dist-info/top_level.txt
micropython_uploader-0.3.2.dist-info/RECORD
