Metadata-Version: 2.1
Name: micropython-uploader
Version: 0.3.2
Summary: UNKNOWN
Home-page: https://github.com/Sapfir0/micropython-uploader
Author: Alex Yurev
Author-email: sapfir999999@yandex.ru
License: MIT
Keywords: hardware micropython circuitpython uploaders upload ampy
Platform: UNKNOWN
Classifier: Development Status :: 2 - Pre-Alpha
Classifier: Intended Audience :: Developers
Classifier: License :: OSI Approved :: MIT License
Classifier: Programming Language :: Python :: 3
Classifier: Programming Language :: Python :: 3.3
Classifier: Programming Language :: Python :: 3.4
Classifier: Programming Language :: Python :: 3.5
Classifier: Programming Language :: Python :: 3.6
Classifier: Programming Language :: Python :: 3.7
Classifier: Programming Language :: Python :: 3.8
Requires-Dist: ampy
